__init__.py
firewall_handler.py
main.py
gpx_merge/__init__.py
gpx_merge/__main__.py
gpx_merge/_version.py
gpx_merge/cli/__init__.py
gpx_merge/cli/__main__.py
gpx_merge/cli/cli.py
gpx_merge/config/__init__.py
gpx_merge/config/config.py
gpx_merge/core/__init__.py
gpx_merge/core/base.py
gpx_merge/core/logging.py
gpx_merge/gui/__init__.py
gpx_merge/gui/__main__.py
gpx_merge/gui/gui.py
gpx_merger-0.0.4.dist-info/licenses/LICENSE
gpx_merger-0.0.4.dist-info/METADATA
gpx_merger-0.0.4.dist-info/WHEEL
gpx_merger-0.0.4.dist-info/entry_points.txt
gpx_merger-0.0.4.dist-info/top_level.txt
gpx_merger-0.0.4.dist-info/RECORD
