Metadata-Version: 2.4
Name: gpx-merger
Version: 0.0.4
Summary: Feature-rich Python project template designed for robustness and ease of use.
Author: pamagister
Requires-Python: <3.12,>=3.10
License-File: LICENSE
Requires-Dist: gpxpy>=1.6.2
Requires-Dist: pydantic>=2.11.7
Requires-Dist: pyyaml>=6.0.2
Requires-Dist: srtm-py>=0.3.7
Provides-Extra: dev
Requires-Dist: pytest>=8.4.0; extra == "dev"
Requires-Dist: pytest-mock>=3.14.1; extra == "dev"
Requires-Dist: coverage>=7.8.2; extra == "dev"
Requires-Dist: flake8>=7.2.0; extra == "dev"
Requires-Dist: black>=25.1.0; extra == "dev"
Requires-Dist: isort>=6.0.1; extra == "dev"
Requires-Dist: pytest-cov>=6.1.1; extra == "dev"
Requires-Dist: mypy>=1.16.0; extra == "dev"
Requires-Dist: gitchangelog>=3.0.4; extra == "dev"
Requires-Dist: pyinstaller>=5.8; extra == "dev"
Requires-Dist: pre-commit>=4.2.0; extra == "dev"
Requires-Dist: ruff>=0.11.13; extra == "dev"
Provides-Extra: docs
Requires-Dist: mkdocs>=1.6.1; extra == "docs"
Requires-Dist: mkdocs-awesome-nav>=2.6.1; extra == "docs"
Requires-Dist: pygments>=2.19.1; extra == "docs"
Dynamic: license-file
